setup_assistant/__init__.py
setup_assistant/cli.py
setup_assistant/core.py
setup_assistant/helpers.py
setup_assistant-0.1.9.dist-info/METADATA
setup_assistant-0.1.9.dist-info/WHEEL
setup_assistant-0.1.9.dist-info/entry_points.txt
setup_assistant-0.1.9.dist-info/top_level.txt
setup_assistant-0.1.9.dist-info/RECORD
